aus/__init__.py
aus/analysis.py
aus/audiofile.py
aus/granulator.py
aus/operations.py
aus/plot.py
aus/sampler.py
aus/setup.py
aus/spectrum.py
aus/synthesis.py
aus_python-0.0.32.dist-info/LICENSE
aus_python-0.0.32.dist-info/METADATA
aus_python-0.0.32.dist-info/WHEEL
aus_python-0.0.32.dist-info/top_level.txt
aus_python-0.0.32.dist-info/RECORD
