Metadata-Version: 2.1
Name: aus-python
Version: 0.0.32
Summary: A package with functionality for offline audio processing
Author: Jeff Martin
Author-email: Jeffrey Martin <jmartin@jeffreymartincomposer.com>
Project-URL: Homepage, https://fleximeter.github.io/
Classifier: Development Status :: 3 - Alpha
Classifier: License :: OSI Approved :: GNU General Public License v3 or later (GPLv3+)
Classifier: Operating System :: OS Independent
Requires-Python: >=3.8
License-File: LICENSE
Requires-Dist: matplotlib
Requires-Dist: numpy
Requires-Dist: pedalboard
Requires-Dist: regex
Requires-Dist: scipy
